proxy/__init__.py
proxy/perf_test.py
proxy/server.py
proxy/transform.py
proxy/pypowerwall/__init__.py
proxy/pypowerwall/__main__.py
proxy/pypowerwall/api_lock.py
proxy/pypowerwall/exceptions.py
proxy/pypowerwall/pypowerwall_base.py
proxy/pypowerwall/regex.py
proxy/pypowerwall/scan.py
proxy/pypowerwall/cloud/__init__.py
proxy/pypowerwall/cloud/decorators.py
proxy/pypowerwall/cloud/exceptions.py
proxy/pypowerwall/cloud/mock_data.py
proxy/pypowerwall/cloud/pypowerwall_cloud.py
proxy/pypowerwall/cloud/stubs.py
proxy/pypowerwall/cloud/teslapy/__init__.py
proxy/pypowerwall/fleetapi/__init__.py
proxy/pypowerwall/fleetapi/__main__.py
proxy/pypowerwall/fleetapi/decorators.py
proxy/pypowerwall/fleetapi/exceptions.py
proxy/pypowerwall/fleetapi/fleetapi.py
proxy/pypowerwall/fleetapi/mock_data.py
proxy/pypowerwall/fleetapi/pypowerwall_fleetapi.py
proxy/pypowerwall/fleetapi/stubs.py
proxy/pypowerwall/local/__init__.py
proxy/pypowerwall/local/exceptions.py
proxy/pypowerwall/local/pypowerwall_local.py
proxy/pypowerwall/local/tesla_pb2.py
proxy/pypowerwall/tedapi/__init__.py
proxy/pypowerwall/tedapi/__main__.py
proxy/pypowerwall/tedapi/decorators.py
proxy/pypowerwall/tedapi/exceptions.py
proxy/pypowerwall/tedapi/mock_data.py
proxy/pypowerwall/tedapi/pypowerwall_tedapi.py
proxy/pypowerwall/tedapi/stubs.py
proxy/pypowerwall/tedapi/tedapi_pb2.py
proxy/pypowerwall/tests/__init__.py
proxy/pypowerwall/tests/test_powerwall.py
proxy/pypowerwall/tests/tedapi/__init__.py
proxy/pypowerwall/tests/tedapi/test_init.py
proxy/pypowerwall/tests/unit/__init__.py
proxy/pypowerwall/tests/unit/test_parse_version.py
proxy/pypowerwall/tests/unit/test_powerwall_core.py
proxy/tests/__init__.py
proxy/tests/test_api_endpoints.py
proxy/tests/test_csv_endpoints.py
pypowerwall/__init__.py
pypowerwall/__main__.py
pypowerwall/api_lock.py
pypowerwall/exceptions.py
pypowerwall/pypowerwall_base.py
pypowerwall/regex.py
pypowerwall/scan.py
pypowerwall/cloud/__init__.py
pypowerwall/cloud/decorators.py
pypowerwall-0.14.9.dist-info/licenses/LICENSE
pypowerwall-0.14.9.dist-info/METADATA
pypowerwall-0.14.9.dist-info/WHEEL
pypowerwall-0.14.9.dist-info/entry_points.txt
pypowerwall-0.14.9.dist-info/top_level.txt
pypowerwall-0.14.9.dist-info/RECORD
