Metadata-Version: 2.4
Name: pypowerwall
Version: 0.14.9
Summary: Python module to access Tesla Energy Gateway for Powerwall and solar power data
Home-page: https://github.com/jasonacox/pypowerwall
Author: Jason Cox
Author-email: jason@jasonacox.com
Classifier: Programming Language :: Python :: 3
Classifier: License :: OSI Approved :: MIT License
Classifier: Operating System :: OS Independent
License-File: LICENSE
Requires-Dist: requests
Requires-Dist: protobuf>=3.20.0
Requires-Dist: python-dotenv
Requires-Dist: pyroute2
Requires-Dist: bs4
Requires-Dist: python-dateutil
Requires-Dist: requests-oauthlib
Requires-Dist: websocket-client>=0.59.0
Dynamic: author
Dynamic: author-email
Dynamic: classifier
Dynamic: description
Dynamic: description-content-type
Dynamic: home-page
Dynamic: license-file
Dynamic: requires-dist
Dynamic: summary
